{
    "metadataKeyClassName": "AddonMetadataKeys",
    "outputDirectory": "AutoGeneratedTopics",
    "topics": [
        {
            "topicName": "BasicControls",
            "subTopics": [
                {
                    "name": "Button",
                    "properties": [
                        { "name": "Content", "type": "object" },
                        { "name": "IsEnabled", "type": "bool" },
                        { "name": "IsDefault", "type": "bool" },
                        { "name": "IsCancel", "type": "bool" },
                        { "name": "IsTabStop", "type": "bool" },
                        { "name": "TabIndex", "type": "int" },
                        { "name": "CommandParameter", "type": "object" },
                        { "name": "CommandTarget", "type": "IInputElement" },
                        { "name": "Background", "type": "Brush" },
                        { "name": "Foreground", "type": "Brush" },
                        { "name": "BorderBrush", "type": "Brush" },
                        { "name": "BorderThickness", "type": "Thickness" },
                        { "name": "FontFamily", "type": "FontFamily" },
                        { "name": "FontSize", "type": "double" },
                        { "name": "FontWeight", "type": "FontWeight" },
                        { "name": "FontStyle", "type": "FontStyle" },
                        { "name": "FontStretch", "type": "FontStretch" },
                        { "name": "Padding", "type": "Thickness" },
                        { "name": "Margin", "type": "Thickness" },
                        { "name": "HorizontalAlignment", "type": "HorizontalAlignment" },
                        { "name": "VerticalAlignment", "type": "VerticalAlignment" },
                        { "name": "HorizontalContentAlignment", "type": "HorizontalAlignment" },
                        { "name": "VerticalContentAlignment", "type": "VerticalAlignment" },
                        { "name": "Width", "type": "double" },
                        { "name": "Height", "type": "double" },
                        { "name": "MinWidth", "type": "double" },
                        { "name": "MinHeight", "type": "double" },
                        { "name": "MaxWidth", "type": "double" },
                        { "name": "MaxHeight", "type": "double" },
                        { "name": "Visibility", "type": "Visibility" },
                        { "name": "ToolTip", "type": "object" },
                        { "name": "Style", "type": "Style" },
                        { "name": "Opacity", "type": "double" },
                        { "name": "Focusable", "type": "bool" },
                        { "name": "Name", "type": "string" },
                        { "name": "Tag", "type": "object" }
                    ]
                },
                {
                    "name": "TextBox",
                    "properties": [
                        { "name": "Text", "type": "string" },
                        { "name": "IsReadOnly", "type": "bool" },
                        { "name": "IsEnabled", "type": "bool" },
                        { "name": "AcceptsReturn", "type": "bool" },
                        { "name": "AcceptsTab", "type": "bool" },
                        { "name": "CaretIndex", "type": "int" },
                        { "name": "MaxLength", "type": "int" },
                        { "name": "TextAlignment", "type": "TextAlignment" },
                        { "name": "TextWrapping", "type": "TextWrapping" },
                        { "name": "HorizontalScrollBarVisibility", "type": "ScrollBarVisibility" },
                        { "name": "VerticalScrollBarVisibility", "type": "ScrollBarVisibility" },
                        { "name": "SelectionStart", "type": "int" },
                        { "name": "SelectionLength", "type": "int" },
                        { "name": "SelectedText", "type": "string" },
                        { "name": "Background", "type": "Brush" },
                        { "name": "Foreground", "type": "Brush" },
                        { "name": "BorderBrush", "type": "Brush" },
                        { "name": "BorderThickness", "type": "Thickness" },
                        { "name": "FontFamily", "type": "FontFamily" },
                        { "name": "FontSize", "type": "double" },
                        { "name": "FontWeight", "type": "FontWeight" },
                        { "name": "FontStyle", "type": "FontStyle" },
                        { "name": "FontStretch", "type": "FontStretch" },
                        { "name": "Padding", "type": "Thickness" },
                        { "name": "Margin", "type": "Thickness" },
                        { "name": "HorizontalAlignment", "type": "HorizontalAlignment" },
                        { "name": "VerticalAlignment", "type": "VerticalAlignment" },
                        { "name": "Width", "type": "double" },
                        { "name": "Height", "type": "double" },
                        { "name": "MinWidth", "type": "double" },
                        { "name": "MinHeight", "type": "double" },
                        { "name": "MaxWidth", "type": "double" },
                        { "name": "MaxHeight", "type": "double" },
                        { "name": "Visibility", "type": "Visibility" },
                        { "name": "ToolTip", "type": "object" },
                        { "name": "Style", "type": "Style" },
                        { "name": "Opacity", "type": "double" },
                        { "name": "Focusable", "type": "bool" },
                        { "name": "Name", "type": "string" },
                        { "name": "Tag", "type": "object" }
                    ]
                },
                {
                    "name": "CheckBox",
                    "properties": [
                        { "name": "IsChecked", "type": "bool?" },
                        { "name": "IsThreeState", "type": "bool" },
                        { "name": "Content", "type": "object" },
                        { "name": "IsEnabled", "type": "bool" },
                        { "name": "IsHitTestVisible", "type": "bool" },
                        { "name": "IsTabStop", "type": "bool" },
                        { "name": "TabIndex", "type": "int" },
                        { "name": "CommandParameter", "type": "object" },
                        { "name": "CommandTarget", "type": "IInputElement" },
                        { "name": "Background", "type": "Brush" },
                        { "name": "Foreground", "type": "Brush" },
                        { "name": "BorderBrush", "type": "Brush" },
                        { "name": "BorderThickness", "type": "Thickness" },
                        { "name": "FontFamily", "type": "FontFamily" },
                        { "name": "FontSize", "type": "double" },
                        { "name": "FontWeight", "type": "FontWeight" },
                        { "name": "FontStyle", "type": "FontStyle" },
                        { "name": "FontStretch", "type": "FontStretch" },
                        { "name": "Padding", "type": "Thickness" },
                        { "name": "Margin", "type": "Thickness" },
                        { "name": "HorizontalAlignment", "type": "HorizontalAlignment" },
                        { "name": "VerticalAlignment", "type": "VerticalAlignment" },
                        { "name": "HorizontalContentAlignment", "type": "HorizontalAlignment" },
                        { "name": "VerticalContentAlignment", "type": "VerticalAlignment" },
                        { "name": "Width", "type": "double" },
                        { "name": "Height", "type": "double" },
                        { "name": "MinWidth", "type": "double" },
                        { "name": "MinHeight", "type": "double" },
                        { "name": "MaxWidth", "type": "double" },
                        { "name": "MaxHeight", "type": "double" },
                        { "name": "Visibility", "type": "Visibility" },
                        { "name": "ToolTip", "type": "object" },
                        { "name": "Style", "type": "Style" },
                        { "name": "Opacity", "type": "double" },
                        { "name": "Focusable", "type": "bool" },
                        { "name": "Name", "type": "string" },
                        { "name": "Tag", "type": "object" }
                    ]
                },
                {
                    "name": "RadioButton",
                    "properties": [
                        { "name": "IsChecked", "type": "bool?" },
                        { "name": "IsThreeState", "type": "bool" },
                        { "name": "GroupName", "type": "string" },
                        { "name": "Content", "type": "object" },
                        { "name": "IsEnabled", "type": "bool" },
                        { "name": "IsHitTestVisible", "type": "bool" },
                        { "name": "IsTabStop", "type": "bool" },
                        { "name": "TabIndex", "type": "int" },
                        { "name": "CommandParameter", "type": "object" },
                        { "name": "CommandTarget", "type": "IInputElement" },
                        { "name": "Background", "type": "Brush" },
                        { "name": "Foreground", "type": "Brush" },
                        { "name": "BorderBrush", "type": "Brush" },
                        { "name": "BorderThickness", "type": "Thickness" },
                        { "name": "FontFamily", "type": "FontFamily" },
                        { "name": "FontSize", "type": "double" },
                        { "name": "FontWeight", "type": "FontWeight" },
                        { "name": "FontStyle", "type": "FontStyle" },
                        { "name": "FontStretch", "type": "FontStretch" },
                        { "name": "Padding", "type": "Thickness" },
                        { "name": "Margin", "type": "Thickness" },
                        { "name": "HorizontalAlignment", "type": "HorizontalAlignment" },
                        { "name": "VerticalAlignment", "type": "VerticalAlignment" },
                        { "name": "HorizontalContentAlignment", "type": "HorizontalAlignment" },
                        { "name": "VerticalContentAlignment", "type": "VerticalAlignment" },
                        { "name": "Width", "type": "double" },
                        { "name": "Height", "type": "double" },
                        { "name": "MinWidth", "type": "double" },
                        { "name": "MinHeight", "type": "double" },
                        { "name": "MaxWidth", "type": "double" },
                        { "name": "MaxHeight", "type": "double" },
                        { "name": "Visibility", "type": "Visibility" },
                        { "name": "ToolTip", "type": "object" },
                        { "name": "Style", "type": "Style" },
                        { "name": "Opacity", "type": "double" },
                        { "name": "Focusable", "type": "bool" },
                        { "name": "Name", "type": "string" },
                        { "name": "Tag", "type": "object" }
                    ]
                },
                {
                    "name": "PasswordBox",
                    "properties": [
                        { "name": "Password", "type": "string" },
                        { "name": "MaxLength", "type": "int" },
                        { "name": "IsEnabled", "type": "bool" },
                        { "name": "IsReadOnly", "type": "bool" },
                        { "name": "IsTabStop", "type": "bool" },
                        { "name": "TabIndex", "type": "int" },
                        { "name": "Background", "type": "Brush" },
                        { "name": "Foreground", "type": "Brush" },
                        { "name": "BorderBrush", "type": "Brush" },
                        { "name": "BorderThickness", "type": "Thickness" },
                        { "name": "FontFamily", "type": "FontFamily" },
                        { "name": "FontSize", "type": "double" },
                        { "name": "FontWeight", "type": "FontWeight" },
                        { "name": "FontStyle", "type": "FontStyle" },
                        { "name": "FontStretch", "type": "FontStretch" },
                        { "name": "Padding", "type": "Thickness" },
                        { "name": "Margin", "type": "Thickness" },
                        { "name": "HorizontalAlignment", "type": "HorizontalAlignment" },
                        { "name": "VerticalAlignment", "type": "VerticalAlignment" },
                        { "name": "Width", "type": "double" },
                        { "name": "Height", "type": "double" },
                        { "name": "MinWidth", "type": "double" },
                        { "name": "MinHeight", "type": "double" },
                        { "name": "MaxWidth", "type": "double" },
                        { "name": "MaxHeight", "type": "double" },
                        { "name": "Visibility", "type": "Visibility" },
                        { "name": "ToolTip", "type": "object" },
                        { "name": "Style", "type": "Style" },
                        { "name": "Opacity", "type": "double" },
                        { "name": "Focusable", "type": "bool" },
                        { "name": "Name", "type": "string" },
                        { "name": "Tag", "type": "object" }
                    ]
                },
                {
                    "name": "Image",
                    "properties": [
                        { "name": "Source", "type": "ImageSource" },
                        { "name": "Stretch", "type": "Stretch" },
                        { "name": "Width", "type": "double" },
                        { "name": "Height", "type": "double" },
                        { "name": "MinWidth", "type": "double" },
                        { "name": "MinHeight", "type": "double" },
                        { "name": "MaxWidth", "type": "double" },
                        { "name": "MaxHeight", "type": "double" },
                        { "name": "Margin", "type": "Thickness" },
                        { "name": "HorizontalAlignment", "type": "HorizontalAlignment" },
                        { "name": "VerticalAlignment", "type": "VerticalAlignment" },
                        { "name": "Opacity", "type": "double" },
                        { "name": "Visibility", "type": "Visibility" },
                        { "name": "ToolTip", "type": "object" },
                        { "name": "Style", "type": "Style" },
                        { "name": "Focusable", "type": "bool" },
                        { "name": "Name", "type": "string" },
                        { "name": "Tag", "type": "object" }
                    ]
                }
            ]
        },
        {
            "topicName": "Panels",
            "subTopics": [
                {
                    "name": "Canvas", 
                    "properties": [
                        { "name": "Background", "type": "Brush" },
                        { "name": "Width", "type": "double" },
                        { "name": "Height", "type": "double" },
                        { "name": "MinWidth", "type": "double" },
                        { "name": "MinHeight", "type": "double" },
                        { "name": "MaxWidth", "type": "double" },
                        { "name": "MaxHeight", "type": "double" },
                        { "name": "Margin", "type": "Thickness" },
                        { "name": "HorizontalAlignment", "type": "HorizontalAlignment" },
                        { "name": "VerticalAlignment", "type": "VerticalAlignment" },
                        { "name": "Opacity", "type": "double" },
                        { "name": "Visibility", "type": "Visibility" },
                        { "name": "ToolTip", "type": "object" },
                        { "name": "Style", "type": "Style" },
                        { "name": "Focusable", "type": "bool" },
                        { "name": "Name", "type": "string" },
                        { "name": "Tag", "type": "object" }
                    ]
                },
                {
                    "name": "WrapPanel", 
                    "properties": [
                        { "name": "ItemHeight", "type": "double" },
                        { "name": "ItemWidth", "type": "double" },
                        { "name": "Width", "type": "double" },
                        { "name": "Height", "type": "double" },
                        { "name": "MinWidth", "type": "double" },
                        { "name": "MinHeight", "type": "double" },
                        { "name": "MaxWidth", "type": "double" },
                        { "name": "MaxHeight", "type": "double" },
                        { "name": "Margin", "type": "Thickness" },
                        { "name": "HorizontalAlignment", "type": "HorizontalAlignment" },
                        { "name": "VerticalAlignment", "type": "VerticalAlignment" },
                        { "name": "Background", "type": "Brush" },
                        { "name": "Opacity", "type": "double" },
                        { "name": "Visibility", "type": "Visibility" },
                        { "name": "ToolTip", "type": "object" },
                        { "name": "Style", "type": "Style" },
                        { "name": "Focusable", "type": "bool" },
                        { "name": "Name", "type": "string" },
                        { "name": "Tag", "type": "object" }
                    ]
                },
                {
                    "name": "StackPanel", 
                    "properties": [
                        { "name": "Width", "type": "double" },
                        { "name": "Height", "type": "double" },
                        { "name": "MinWidth", "type": "double" },
                        { "name": "MinHeight", "type": "double" },
                        { "name": "MaxWidth", "type": "double" },
                        { "name": "MaxHeight", "type": "double" },
                        { "name": "Margin", "type": "Thickness" },
                        { "name": "HorizontalAlignment", "type": "HorizontalAlignment" },
                        { "name": "VerticalAlignment", "type": "VerticalAlignment" },
                        { "name": "Background", "type": "Brush" },
                        { "name": "Opacity", "type": "double" },
                        { "name": "Visibility", "type": "Visibility" },
                        { "name": "ToolTip", "type": "object" },
                        { "name": "Style", "type": "Style" },
                        { "name": "Focusable", "type": "bool" },
                        { "name": "Name", "type": "string" },
                        { "name": "Tag", "type": "object" }
                    ]
                },
                {
                    "name": "DockPanel", 
                    "properties": [
                        { "name": "LastChildFill", "type": "bool" },
                        { "name": "Width", "type": "double" },
                        { "name": "Height", "type": "double" },
                        { "name": "MinWidth", "type": "double" },
                        { "name": "MinHeight", "type": "double" },
                        { "name": "MaxWidth", "type": "double" },
                        { "name": "MaxHeight", "type": "double" },
                        { "name": "Margin", "type": "Thickness" },
                        { "name": "HorizontalAlignment", "type": "HorizontalAlignment" },
                        { "name": "VerticalAlignment", "type": "VerticalAlignment" },
                        { "name": "Background", "type": "Brush" },
                        { "name": "Opacity", "type": "double" },
                        { "name": "Visibility", "type": "Visibility" },
                        { "name": "ToolTip", "type": "object" },
                        { "name": "Style", "type": "Style" },
                        { "name": "Focusable", "type": "bool" },
                        { "name": "Name", "type": "string" },
                        { "name": "Tag", "type": "object" }
                    ]
                },
                {
                    "name": "Grid" ,
                    "properties": [
                        { "name": "ShowGridLines", "type": "bool" },
                        { "name": "Width", "type": "double" },
                        { "name": "Height", "type": "double" },
                        { "name": "MinWidth", "type": "double" },
                        { "name": "MinHeight", "type": "double" },
                        { "name": "MaxWidth", "type": "double" },
                        { "name": "MaxHeight", "type": "double" },
                        { "name": "Margin", "type": "Thickness" },
                        { "name": "HorizontalAlignment", "type": "HorizontalAlignment" },
                        { "name": "VerticalAlignment", "type": "VerticalAlignment" },
                        { "name": "Background", "type": "Brush" },
                        { "name": "Opacity", "type": "double" },
                        { "name": "Visibility", "type": "Visibility" },
                        { "name": "ToolTip", "type": "object" },
                        { "name": "Style", "type": "Style" },
                        { "name": "Focusable", "type": "bool" },
                        { "name": "Name", "type": "string" },
                        { "name": "Tag", "type": "object" }
                    ]
                }
            ]
        }
    ]
}